huanyue/__init__.py
huanyue/openImg.py
huanyue-0.0.1.dist-info/METADATA
huanyue-0.0.1.dist-info/WHEEL
huanyue-0.0.1.dist-info/top_level.txt
huanyue-0.0.1.dist-info/RECORD
